pyGarufa/__init__.py
pyGarufa/service.py
pyGarufa/clients/__init__.py
pyGarufa/clients/rest_rfx.py
pyGarufa/clients/websocket_rfx.py
pyGarufa/components/__init__.py
pyGarufa/components/enums.py
pyGarufa/components/exceptions.py
pyGarufa/components/globals.py
pyGarufa/components/messages.py
pyGarufa/components/urls.py
pyGarufa-0.0.5.dist-info/METADATA
pyGarufa-0.0.5.dist-info/WHEEL
pyGarufa-0.0.5.dist-info/top_level.txt
pyGarufa-0.0.5.dist-info/RECORD
