Metadata-Version: 2.1
Name: pyGarufa
Version: 0.0.5
Summary: Python connector for ROFEX's Rest and Websocket APIs. For multiples comitentes
Home-page: https://github.com/garufa-invex/pyGarufa
Author: Diego Garbiglia
Author-email: diegogarbiglia@gmail.com
Classifier: Programming Language :: Python :: 3
Classifier: License :: OSI Approved :: MIT License
Classifier: Operating System :: OS Independent
Classifier: Development Status :: 4 - Beta
Classifier: Intended Audience :: Developers
Classifier: Intended Audience :: Information Technology
Classifier: Intended Audience :: Science/Research
Classifier: Topic :: Office/Business :: Financial :: Investment
Classifier: Topic :: Software Development
Requires-Dist: requests >=2.20.0
Requires-Dist: simplejson >=3.10.0
Requires-Dist: enum34 >=1.1.6
Requires-Dist: websocket-client >=1.6.4
